fly_tracker/.DS_Store
fly_tracker/Scraper.py
fly_tracker/__init__.py
fly_tracker/__main__.py
fly_tracker/testing/.DS_Store
fly_tracker/testing/__init__.py
fly_tracker/testing/integration_tests.py
fly_tracker/testing/test_all.py
fly_tracker/testing/test_data.json
fly_tracker/testing/test_source_page.html
fly_tracker-0.0.1.dist-info/LICENSE
fly_tracker-0.0.1.dist-info/METADATA
fly_tracker-0.0.1.dist-info/WHEEL
fly_tracker-0.0.1.dist-info/top_level.txt
fly_tracker-0.0.1.dist-info/RECORD
