Metadata-Version: 2.1
Name: fly-tracker
Version: 0.0.1
Summary: The Fly Tracker library lets you monitor the flight prices for any route. The user has the option to set up notifications for the tracked route which can help him book tickets when he wants to.
Author-email: Ritik Panda <ritik.panda@columbia.edu>
License: MIT License
Project-URL: repository, https://github.com/Ritik3111/fly_tracker
Classifier: Development Status :: 2 - Pre-Alpha
Classifier: Programming Language :: Python :: Implementation :: CPython
Classifier: Programming Language :: Python :: Implementation :: PyPy
Classifier: Programming Language :: Python :: 3
Classifier: Programming Language :: Python :: 3.7
Classifier: Programming Language :: Python :: 3.8
Classifier: Programming Language :: Python :: 3.9
Classifier: Programming Language :: Python :: 3.10
Classifier: Programming Language :: Python :: 3.11
Requires-Python: >=3.7
License-File: LICENSE
Provides-Extra: develop
Requires-Dist: black (>=22) ; extra == 'develop'
Requires-Dist: bump2version (>=1.0.0) ; extra == 'develop'
Requires-Dist: check-manifest ; extra == 'develop'
Requires-Dist: flake8 (>=3.7.8) ; extra == 'develop'
Requires-Dist: flake8-black (>=0.2.1) ; extra == 'develop'
Requires-Dist: flake8-pyproject ; extra == 'develop'
Requires-Dist: mypy ; extra == 'develop'
Requires-Dist: pytest (>=4.3.0) ; extra == 'develop'
Requires-Dist: pytest-cov (>=2.6.1) ; extra == 'develop'
Requires-Dist: twine ; extra == 'develop'
Requires-Dist: wheel ; extra == 'develop'
